odoo10_addon_account_bank_statement_import_fr_cfonb-10.0.1.0.0.99.dev8-nspkg.pth
odoo/addons/account_bank_statement_import_fr_cfonb/README.rst
odoo/addons/account_bank_statement_import_fr_cfonb/__init__.py
odoo/addons/account_bank_statement_import_fr_cfonb/__manifest__.py
odoo/addons/account_bank_statement_import_fr_cfonb/i18n/account_bank_statement_import_fr_cfonb.pot
odoo/addons/account_bank_statement_import_fr_cfonb/i18n/nb_NO.po
odoo/addons/account_bank_statement_import_fr_cfonb/models/__init__.py
odoo/addons/account_bank_statement_import_fr_cfonb/models/account_bank_statement_import.py
odoo/addons/account_bank_statement_import_fr_cfonb/static/description/icon.png
odoo/addons/account_bank_statement_import_fr_cfonb/views/account_bank_statement_import.xml
odoo10_addon_account_bank_statement_import_fr_cfonb-10.0.1.0.0.99.dev8.dist-info/METADATA
odoo10_addon_account_bank_statement_import_fr_cfonb-10.0.1.0.0.99.dev8.dist-info/WHEEL
odoo10_addon_account_bank_statement_import_fr_cfonb-10.0.1.0.0.99.dev8.dist-info/namespace_packages.txt
odoo10_addon_account_bank_statement_import_fr_cfonb-10.0.1.0.0.99.dev8.dist-info/top_level.txt
odoo10_addon_account_bank_statement_import_fr_cfonb-10.0.1.0.0.99.dev8.dist-info/RECORD
